README.md
setup.py
kinet/__init__.py
kinet/kinet.py
kinet.egg-info/PKG-INFO
kinet.egg-info/SOURCES.txt
kinet.egg-info/dependency_links.txt
kinet.egg-info/top_level.txt