Metadata-Version: 1.1
Name: kinet
Version: 0.3.0
Summary: library for controlling color kinetics lights
Home-page: https://github.com/Firescar96/kinet
Author: Nchinda2
Author-email: nchinda2@gmail.com
License: UNKNOWN
Platform: UNKNOWN
Classifier: Programming Language :: Python
Classifier: Programming Language :: Python :: 2
Classifier: License :: OSI Approved :: GNU General Public License v3 (GPLv3)
Classifier: Operating System :: OS Independent
Classifier: Environment :: Console
